{
  "mei 2026": [
    [
      {
        "dag": "",
        "tijden": []
      },
      {
        "dag": "zo. zondag 24 mei",
        "tijden": [
          "02:19 (laagwater)"
        ]
      },
      {
        "dag": "(Pinksteren / Pinksterzondag / Eerste Pinksterdag)",
        "tijden": [
          "08:33 (hoogwater)"
        ]
      }
    ],
    [
      {
        "dag": "",
        "tijden": [
          "14:49 (laagwater)"
        ]
      },
      {
        "dag": "",
        "tijden": [
          "21:02 (hoogwater)"
        ]
      },
      {
        "dag": "ma. maandag 25 mei",
        "tijden": [
          "03:21 (laagwater)"
        ]
      }
    ],
    [
      {
        "dag": "(Pinkstermaandag / Tweede Pinksterdag)",
        "tijden": [
          "09:41 (hoogwater)"
        ]
      },
      {
        "dag": "",
        "tijden": [
          "15:53 (laagwater)"
        ]
      },
      {
        "dag": "",
        "tijden": [
          "22:06 (hoogwater)"
        ]
      }
    ],
    [
      {
        "dag": "di. dinsdag 26 mei",
        "tijden": [
          "04:29 (laagwater)"
        ]
      },
      {
        "dag": "",
        "tijden": [
          "10:45 (hoogwater)"
        ]
      },
      {
        "dag": "",
        "tijden": [
          "17:11 (laagwater)"
        ]
      }
    ],
    [
      {
        "dag": "",
        "tijden": [
          "23:06 (hoogwater)"
        ]
      }
    ]
  ],
  "juni 2026": [
    [
      {
        "dag": "",
        "tijden": []
      },
      {
        "dag": "ma. maandag 1 juni",
        "tijden": [
          "02:45 (hoogwater)"
        ]
      },
      {
        "dag": "",
        "tijden": [
          "09:07 (laagwater)"
        ]
      }
    ],
    [
      {
        "dag": "",
        "tijden": [
          "15:09 (hoogwater)"
        ]
      },
      {
        "dag": "",
        "tijden": [
          "21:24 (laagwater)"
        ]
      },
      {
        "dag": "di. dinsdag 2 juni",
        "tijden": [
          "03:19 (hoogwater)"
        ]
      }
    ],
    [
      {
        "dag": "",
        "tijden": [
          "09:34 (laagwater)"
        ]
      },
      {
        "dag": "",
        "tijden": [
          "15:41 (hoogwater)"
        ]
      },
      {
        "dag": "",
        "tijden": [
          "21:53 (laagwater)"
        ]
      }
    ],
    [
      {
        "dag": "wo. woensdag 3 juni",
        "tijden": [
          "03:50 (hoogwater)"
        ]
      },
      {
        "dag": "",
        "tijden": [
          "10:05 (laagwater)"
        ]
      },
      {
        "dag": "",
        "tijden": [
          "16:09 (hoogwater)"
        ]
      }
    ],
    [
      {
        "dag": "",
        "tijden": [
          "22:22 (laagwater)"
        ]
      }
    ]
  ]
}