{
  "oktober 2025": [
    [
      {
        "dag": "",
        "tijden": []
      },
      {
        "dag": "di. dinsdag 14 okt oktober",
        "tijden": [
          "01:18 (laagwater)"
        ]
      },
      {
        "dag": "",
        "tijden": [
          "07:21 (hoogwater)"
        ]
      }
    ],
    [
      {
        "dag": "",
        "tijden": [
          "13:50 (laagwater)"
        ]
      },
      {
        "dag": "",
        "tijden": [
          "20:07 (hoogwater)"
        ]
      },
      {
        "dag": "wo. woensdag 15 okt oktober",
        "tijden": [
          "02:35 (laagwater)"
        ]
      }
    ],
    [
      {
        "dag": "",
        "tijden": [
          "08:46 (hoogwater)"
        ]
      },
      {
        "dag": "",
        "tijden": [
          "15:12 (laagwater)"
        ]
      },
      {
        "dag": "",
        "tijden": [
          "21:36 (hoogwater)"
        ]
      }
    ],
    [
      {
        "dag": "do. donderdag 16 okt oktober",
        "tijden": [
          "03:56 (laagwater)"
        ]
      },
      {
        "dag": "",
        "tijden": [
          "10:12 (hoogwater)"
        ]
      },
      {
        "dag": "",
        "tijden": [
          "16:33 (laagwater)"
        ]
      }
    ],
    [
      {
        "dag": "",
        "tijden": [
          "23:00 (hoogwater)"
        ]
      }
    ]
  ]
}